swiftpy/__init__.py
swiftpy/auth.py
swiftpy/db.py
swiftpy/home.py
swiftpy/schema.sql
swiftpy-0.0.3.dist-info/METADATA
swiftpy-0.0.3.dist-info/WHEEL
swiftpy-0.0.3.dist-info/top_level.txt
swiftpy-0.0.3.dist-info/RECORD
