Metadata-Version: 2.1
Name: swiftpy
Version: 0.0.3
Summary: Tracking server for SwiftAce Python SDK
Home-page: https://swiftace.ai/
Author: Siddhant U (SwiftAce)
Author-email: opensource@swiftace.ai
License: UNKNOWN
Platform: UNKNOWN
Classifier: Programming Language :: Python :: 3
Classifier: License :: OSI Approved :: MIT License
Classifier: Operating System :: OS Independent
Requires-Dist: flask
